dist_builder.py
dist_builder-0.3.0.dist-info/METADATA
dist_builder-0.3.0.dist-info/RECORD
dist_builder-0.3.0.dist-info/WHEEL
dist_builder-0.3.0.dist-info/top_level.txt
