Metadata-Version: 2.1
Name: dist-builder
Version: 0.3.0
Summary: Build a wheel and source distribution and bundle with other files in a zip
Home-page: https://github.com/dnut/dist-builder/
Author: Drew Nutter
Author-email: drew@drewnutter.com
License: GPLv3
Platform: UNKNOWN
